[
	{
		"name": "Eras Bold",
		"items": [
			"wisky",
			"beer",
			"chocolate",
			"darth vader armor",
			"clothes",
			"nice clothes",
			"liquid joy",
			"hot chocolate",
			"herbal tea",
			"headphones",
			"coffie",
			"tea",
			"carrot",
			"veggie smoothie"
		],
		"moves":[],
		"equipped":[],
		"repeat_dialog":{
			"hi, do you wanna buy something?": "_trade"
		},
		"dialog":{"battle_none":{}, "battle_won":{}, "battle_lost":{}},
		"stats":{
			"determination": 100,
			"enlightenment": 50,
			"focus": 15,
			"hope": 25,
			"control": 30,
			"thought": 100
		},
		"losing_message": "dammit",
		"battle_name": "Eras Bold"
	},
	{
		"name": "Lucida Bright",
		"items":[],
		"equipped":[],
		"moves":[
			"Form theory",
			"Agape",
			"mission statment",
			"Libertarianism"
		],
		"stats":{
			"determination": 200,
			"enlightenment": 75,
			"focus": 5,
			"hope": 20,
			"control": 5,
			"thought": 250
		},
		"losing_message": "I.. Am.. Not.. Your.... ",
		"battle_name": "beauty",
		"dialog":{
			"battle_lost":{
				"moonlight-scene":{
					"I don't think they're out here to hurts us, not theese": "nobodies harmed right?"
				},
				"default":{}
			},
			"battle_won":{
				"moonlight-scene":{
					"what.. did it just say?": "if not.. what are..."
				},
				"default":{}
			},
			"battle_none":{
				"house2-interior":{
					"me and richard are going on a walk do you want to come?": { "yup": "okay see you there!", "no thanks": "well if you carry on left, you'll find us."}
				},
				"overworld":{
					"hi Im Lucidia, You Okay? it looked like you blacked out for a bit.":""
				}
			}
		},
		"repeat_dialog": { "..." : ""}
	},
	{
		"name": "Cooper Black",
		"items":[],
		"equipped":[],
		"moves":[],
		"stats":{
			"determination": 150,
			"enlightenment": 100,
			"focus": 10,
			"hope": 10,
			"control": 20,
			"thought": 100
		},
		"losing_message": "...as we forgive those who trespassed against us",
		"dialog":{
			"battle_lost":{
			},
			"battle_won":{
			},
			"no_battle":{
				"house2-interior":{
					"ah hello, I am Cooper black, nice to meet you." : " i welcome you to the village of lleh",
					"in this village due to a dark magic, emotions manifest themselves as human" : "and fight us until we only become that emotion"
				},
				"moonlight-scene":{
					"Well, that was uncalled for." : "you know you could of just turned the off switch at the back"
				}
			}
		},
		"repeat_dialog": { "..." : ""}
	},
	{
		"name": "Poor Richard",
		"items":[],
		"equipped":[],
		"moves":[],
		"stats":{
			"determination": 200,
			"enlightenment": 75,
			"focus": 5,
			"hope": 20,
			"control": 5,
			"thought": 100
		},
		"losing_message": "...",
		"dialog":{
			"battle_lost":{
				"default":{}
			},
			"battle_won":{
				"default":{}
			},
			"battle_none":{
			}
		},
		"repeat_dialog": { "..." : ""}
	},
	{
		"name": "Candara",
		"battle_name": "Panic",
		"items":[],
		"equipped":[],
		"moves":[],
		"stats":{
			"determination": 200,
			"enlightenment": 75,
			"focus": 5,
			"hope": 20,
			"control": 5,
			"thought": 200
		},
		"losing_message": "...",
		"dialog":{
			"battle_lost":{
				"default":{}
			},
			"battle_won":{
				"default":{}
			},
			"battle_none":{
			}
		},
		"repeat_dialog": { "..." : ""}
	}
]


	





